scfetch/__main__.py
scfetch/arch.py
scfetch/ascii.py
scfetch/battery.py
scfetch/config.py
scfetch/cpu.py
scfetch/de_wm.py
scfetch/disk_usage.py
scfetch/gpu.py
scfetch/kernel_ver.py
scfetch/locale_info.py
scfetch/mac.py
scfetch/machine_name.py
scfetch/os_info.py
scfetch/pc.py
scfetch/private_ip.py
scfetch/public_ip.py
scfetch/python_version.py
scfetch/ram.py
scfetch/screen_resolution.py
scfetch/shell.py
scfetch/uptime.py
scfetch/user.py
scfetch-2.3.1.dist-info/LICENSE
scfetch-2.3.1.dist-info/METADATA
scfetch-2.3.1.dist-info/WHEEL
scfetch-2.3.1.dist-info/entry_points.txt
scfetch-2.3.1.dist-info/top_level.txt
scfetch-2.3.1.dist-info/RECORD
