Metadata-Version: 2.2
Name: scfetch
Version: 2.3.1
Summary: minimal fetch program for windows, linux and macos
Author-email: sctech <gamerselimiko@gmail.com>
Project-URL: source, https://github.com/sctech-tr/scfetch
Classifier: Programming Language :: Python :: 3
Classifier: Programming Language :: Python :: 3.12
Classifier: Programming Language :: Python :: 3.13
Classifier: Programming Language :: Python :: 3 :: Only
Classifier: Intended Audience :: End Users/Desktop
Classifier: Intended Audience :: Developers
Classifier: Natural Language :: English
Classifier: Programming Language :: Python :: Implementation :: CPython
Classifier: Topic :: System :: Operating System
Classifier: License :: OSI Approved :: MIT License
Classifier: Operating System :: Microsoft :: Windows :: Windows 10
Classifier: Operating System :: Microsoft :: Windows :: Windows 11
Classifier: Operating System :: Microsoft :: Windows
Classifier: Operating System :: POSIX :: Linux
Classifier: Operating System :: MacOS
Requires-Python: >=3.12
License-File: LICENSE
Requires-Dist: colorist
Requires-Dist: psutil
Requires-Dist: screeninfo
Requires-Dist: requests
